SrgLib-1.1.0.dist-info/DESCRIPTION.rst
SrgLib-1.1.0.dist-info/METADATA
SrgLib-1.1.0.dist-info/RECORD
SrgLib-1.1.0.dist-info/WHEEL
SrgLib-1.1.0.dist-info/metadata.json
SrgLib-1.1.0.dist-info/top_level.txt
srg/__init__.py
srg/mappings.py
srg/output.py
srg/parser.py
srg/types.py
