Metadata-Version: 2.0
Name: SrgLib
Version: 1.1.0
Summary: A python library for handling srg files and related stuff)
Home-page: UNKNOWN
Author: Techcable
Author-email: UNKNOWN
License: UNKNOWN
Platform: UNKNOWN
